
[
    {
        "id": 155,
        "distance": "0.21642513448611",
        "note": "0",
        "idnodea": 1368366564,
        "lata": "45.7680606",
        "lona": "4.8586757",
        "idnodeb": 1778350879,
        "latb": "45.7662444",
        "lonb": "4.8590629"
    },
    {
        "id": 156,
        "distance": "0.036932382325861",
        "note": "0",
        "idnodea": 26035069,
        "lata": "45.7659102",
        "lona": "4.859239",
        "idnodeb": 26035070,
        "latb": "45.7662421",
        "lonb": "4.8592204"
    },
    {
        "id": 182,
        "distance": "0.02219434369994",
        "note": "0",
        "idnodea": 26035131,
        "lata": "45.7662401",
        "lona": "4.8595064",
        "idnodeb": 26035070,
        "latb": "45.7662421",
        "lonb": "4.8592204"
    },
    {
        "id": 283,
        "distance": "0.02513041457199",
        "note": "0",
        "idnodea": 1368366566,
        "lata": "45.7682081",
        "lona": "4.8589294",
        "idnodeb": 378175582,
        "latb": "45.7683425",
        "lonb": "4.8591899"
    },
    {
        "id": 290,
        "distance": "0.057165722126267",
        "note": "0",
        "idnodea": 25468012,
        "lata": "45.7672997",
        "lona": "4.863354",
        "idnodeb": 25468021,
        "latb": "45.7672903",
        "lonb": "4.8626171"
    },
    {
        "id": 291,
        "distance": "0.063610177601165",
        "note": "0",
        "idnodea": 25468021,
        "lata": "45.7672903",
        "lona": "4.8626171",
        "idnodeb": 25468023,
        "latb": "45.7672665",
        "lonb": "4.8617977"
    },
    {
        "id": 294,
        "distance": "0.12548217551402",
        "note": "0",
        "idnodea": 25468013,
        "lata": "45.7680762",
        "lona": "4.8657959",
        "idnodeb": 25468027,
        "latb": "45.7683838",
        "lonb": "4.8672869"
    },
    {
        "id": 311,
        "distance": "0.037290260325931",
        "note": "0",
        "idnodea": 378212455,
        "lata": "45.7687038",
        "lona": "4.8619835",
        "idnodeb": 1678246930,
        "latb": "45.7687131",
        "lonb": "4.8624641"
    },
    {
        "id": 314,
        "distance": "0.054008244317195",
        "note": "0",
        "idnodea": 1678246930,
        "lata": "45.7687131",
        "lona": "4.8624641",
        "idnodeb": 26295043,
        "latb": "45.7687281",
        "lonb": "4.8631601"
    },
    {
        "id": 317,
        "distance": "0.0034905604922391",
        "note": "0",
        "idnodea": 26295043,
        "lata": "45.7687281",
        "lona": "4.8631601",
        "idnodeb": 1439736118,
        "latb": "45.7687292",
        "lonb": "4.8632051"
    },
    {
        "id": 1394,
        "distance": "0.064311116222782",
        "note": "0",
        "idnodea": 25468031,
        "lata": "45.7663518",
        "lona": "4.8680071",
        "idnodeb": 25468030,
        "latb": "45.7663331",
        "lonb": "4.8671784"
    },
    {
        "id": 1396,
        "distance": "0.22817188142178",
        "note": "0",
        "idnodea": 25468030,
        "lata": "45.7663331",
        "lona": "4.8671784",
        "idnodeb": 25468027,
        "latb": "45.7683838",
        "lonb": "4.8672869"
    },
    {
        "id": 1397,
        "distance": "0.10402235898082",
        "note": "0",
        "idnodea": 25468030,
        "lata": "45.7663331",
        "lona": "4.8671784",
        "idnodeb": 25468005,
        "latb": "45.7663331",
        "lonb": "4.8658373"
    },
    {
        "id": 1402,
        "distance": "0.13019681371574",
        "note": "0",
        "idnodea": 25468003,
        "lata": "45.7663306",
        "lona": "4.8634654",
        "idnodeb": 25468008,
        "latb": "45.7651638",
        "lonb": "4.8636063"
    },
    {
        "id": 1404,
        "distance": "0.078242773293116",
        "note": "0",
        "idnodea": 25468005,
        "lata": "45.7663331",
        "lona": "4.8658373",
        "idnodeb": 25468004,
        "latb": "45.7663181",
        "lonb": "4.8648288"
    },
    {
        "id": 1405,
        "distance": "0.10580113319588",
        "note": "0",
        "idnodea": 25468004,
        "lata": "45.7663181",
        "lona": "4.8648288",
        "idnodeb": 25468003,
        "latb": "45.7663306",
        "lonb": "4.8634654"
    },
    {
        "id": 1406,
        "distance": "0.44782775214496",
        "note": "0",
        "idnodea": 25468004,
        "lata": "45.7663181",
        "lona": "4.8648288",
        "idnodeb": 25468011,
        "latb": "45.7671788",
        "lonb": "4.8647966"
    },
    {
        "id": 1407,
        "distance": "0.13374881260087",
        "note": "0",
        "idnodea": 25468009,
        "lata": "45.7666998",
        "lona": "4.8634341",
        "idnodeb": 25468011,
        "latb": "45.7671788",
        "lonb": "4.8647966"
    },
    {
        "id": 1414,
        "distance": "0.071780558646803",
        "note": "0",
        "idnodea": 54704569,
        "lata": "45.7652108",
        "lona": "4.8688754",
        "idnodeb": 25468033,
        "latb": "45.7652148",
        "lonb": "4.86795"
    },
    {
        "id": 1415,
        "distance": "0.12649918007115",
        "note": "0",
        "idnodea": 25468031,
        "lata": "45.7663518",
        "lona": "4.8680071",
        "idnodeb": 25468033,
        "latb": "45.7652148",
        "lonb": "4.86795"
    },
    {
        "id": 1417,
        "distance": "0.06481301266765",
        "note": "0",
        "idnodea": 25468033,
        "lata": "45.7652148",
        "lona": "4.86795",
        "idnodeb": 25468032,
        "latb": "45.7652018",
        "lonb": "4.8671146"
    },
    {
        "id": 1419,
        "distance": "0.12588499428707",
        "note": "0",
        "idnodea": 25468032,
        "lata": "45.7652018",
        "lona": "4.8671146",
        "idnodeb": 25468030,
        "latb": "45.7663331",
        "lonb": "4.8671784"
    },
    {
        "id": 1420,
        "distance": "0.098481907000503",
        "note": "0",
        "idnodea": 25468032,
        "lata": "45.7652018",
        "lona": "4.8671146",
        "idnodeb": 25468006,
        "latb": "45.7651876",
        "lonb": "4.8658451"
    },
    {
        "id": 1421,
        "distance": "0.12736840007309",
        "note": "0",
        "idnodea": 25468005,
        "lata": "45.7663331",
        "lona": "4.8658373",
        "idnodeb": 25468006,
        "latb": "45.7651876",
        "lonb": "4.8658451"
    },
    {
        "id": 1423,
        "distance": "0.076372027088493",
        "note": "0",
        "idnodea": 25468006,
        "lata": "45.7651876",
        "lona": "4.8658451",
        "idnodeb": 25468007,
        "latb": "45.7651655",
        "lonb": "4.864861"
    },
    {
        "id": 1425,
        "distance": "0.12818073062771",
        "note": "0",
        "idnodea": 25468007,
        "lata": "45.7651655",
        "lona": "4.864861",
        "idnodeb": 25468004,
        "latb": "45.7663181",
        "lonb": "4.8648288"
    },
    {
        "id": 1426,
        "distance": "0.097340556259211",
        "note": "0",
        "idnodea": 25468007,
        "lata": "45.7651655",
        "lona": "4.864861",
        "idnodeb": 25468008,
        "latb": "45.7651638",
        "lonb": "4.8636063"
    },
    {
        "id": 1429,
        "distance": "0.12608095758678",
        "note": "0",
        "idnodea": 25468025,
        "lata": "45.7651705",
        "lona": "4.8618838",
        "idnodeb": 25468022,
        "latb": "45.7663029",
        "lonb": "4.8618177"
    },
    {
        "id": 1431,
        "distance": "0.065974687653862",
        "note": "0",
        "idnodea": 25468008,
        "lata": "45.7651638",
        "lona": "4.8636063",
        "idnodeb": 25468076,
        "latb": "45.7651564",
        "lonb": "4.8627558"
    },
    {
        "id": 1432,
        "distance": "0.067657295590646",
        "note": "0",
        "idnodea": 25468076,
        "lata": "45.7651564",
        "lona": "4.8627558",
        "idnodeb": 25468025,
        "latb": "45.7651705",
        "lonb": "4.8618838"
    },
    {
        "id": 1449,
        "distance": "0.029945341835155",
        "note": "0",
        "idnodea": 26035011,
        "lata": "45.7685297",
        "lona": "4.8585705",
        "idnodeb": 26035009,
        "latb": "45.7685061",
        "lonb": "4.8581859"
    },
    {
        "id": 1450,
        "distance": "0.093961092441756",
        "note": "0",
        "idnodea": 26035009,
        "lata": "45.7685061",
        "lona": "4.8581859",
        "idnodeb": 25310866,
        "latb": "45.7683986",
        "lonb": "4.8569843"
    },
    {
        "id": 1451,
        "distance": "0.20624890719903",
        "note": "0",
        "idnodea": 26035009,
        "lata": "45.7685061",
        "lona": "4.8581859",
        "idnodeb": 26035015,
        "latb": "45.7678961",
        "lonb": "4.8581075"
    },
    {
        "id": 1453,
        "distance": "0.089015974544511",
        "note": "0",
        "idnodea": 2072612784,
        "lata": "45.7651923",
        "lona": "4.8571395",
        "idnodeb": 26035106,
        "latb": "45.7651118",
        "lonb": "4.8559977"
    },
    {
        "id": 1455,
        "distance": "0.088574914973818",
        "note": "0",
        "idnodea": 26035106,
        "lata": "45.7651118",
        "lona": "4.8559977",
        "idnodeb": 1954994781,
        "latb": "45.765903",
        "lonb": "4.8558648"
    },
    {
        "id": 1744,
        "distance": "0.062627355597798",
        "note": "0",
        "idnodea": 54704534,
        "lata": "45.765248",
        "lona": "4.8715925",
        "idnodeb": 54704586,
        "latb": "45.7652325",
        "lonb": "4.8707854"
    },
    {
        "id": 1745,
        "distance": "0.066621719866951",
        "note": "0",
        "idnodea": 54704586,
        "lata": "45.7652325",
        "lona": "4.8707854",
        "idnodeb": 54704577,
        "latb": "45.7652296",
        "lonb": "4.8699265"
    },
    {
        "id": 1750,
        "distance": "0.0647580678309",
        "note": "0",
        "idnodea": 54704596,
        "lata": "45.7674401",
        "lona": "4.8688821",
        "idnodeb": 25468029,
        "latb": "45.7674433",
        "lonb": "4.8680472"
    },
    {
        "id": 1752,
        "distance": "0.12140336569366",
        "note": "0",
        "idnodea": 25468029,
        "lata": "45.7674433",
        "lona": "4.8680472",
        "idnodeb": 25468031,
        "latb": "45.7663518",
        "lonb": "4.8680071"
    },
    {
        "id": 1753,
        "distance": "0.062586787453811",
        "note": "0",
        "idnodea": 25468029,
        "lata": "45.7674433",
        "lona": "4.8680472",
        "idnodeb": 25468028,
        "latb": "45.767447",
        "lonb": "4.8672403"
    },
    {
        "id": 1755,
        "distance": "0.10422512306618",
        "note": "0",
        "idnodea": 25468028,
        "lata": "45.767447",
        "lona": "4.8672403",
        "idnodeb": 25468027,
        "latb": "45.7683838",
        "lonb": "4.8672869"
    },
    {
        "id": 1756,
        "distance": "0.11080006454203",
        "note": "0",
        "idnodea": 25468028,
        "lata": "45.767447",
        "lona": "4.8672403",
        "idnodeb": 25468014,
        "latb": "45.76746",
        "lonb": "4.8658119"
    },
    {
        "id": 1757,
        "distance": "0.068526180348413",
        "note": "0",
        "idnodea": 25468013,
        "lata": "45.7680762",
        "lona": "4.8657959",
        "idnodeb": 25468014,
        "latb": "45.76746",
        "lonb": "4.8658119"
    },
    {
        "id": 1758,
        "distance": "0.1253150351495",
        "note": "0",
        "idnodea": 25468014,
        "lata": "45.76746",
        "lona": "4.8658119",
        "idnodeb": 25468005,
        "latb": "45.7663331",
        "lonb": "4.8658373"
    },
    {
        "id": 3785,
        "distance": "0.05324478983888",
        "note": "0",
        "idnodea": 2188469195,
        "lata": "45.7666671",
        "lona": "4.8567644",
        "idnodeb": 25310911,
        "latb": "45.7671411",
        "lonb": "4.8566668"
    },
    {
        "id": 3786,
        "distance": "0.018043083165704",
        "note": "0",
        "idnodea": 270733389,
        "lata": "45.7671654",
        "lona": "4.8568968",
        "idnodeb": 25310911,
        "latb": "45.7671411",
        "lonb": "4.8566668"
    },
    {
        "id": 3787,
        "distance": "0.079271195881105",
        "note": "0",
        "idnodea": 25310911,
        "lata": "45.7671411",
        "lona": "4.8566668",
        "idnodeb": 25310874,
        "latb": "45.7670571",
        "lonb": "4.8556519"
    },
    {
        "id": 3899,
        "distance": "0.15140181901661",
        "note": "0",
        "idnodea": 54704569,
        "lata": "45.7652108",
        "lona": "4.8688754",
        "idnodeb": 54704572,
        "latb": "45.7665722",
        "lonb": "4.8688951"
    },
    {
        "id": 4581,
        "distance": "0.10813639424923",
        "note": "0",
        "idnodea": 376377850,
        "lata": "45.7672616",
        "lona": "4.8616329",
        "idnodeb": 376378078,
        "latb": "45.7662909",
        "lonb": "4.861693"
    },
    {
        "id": 4583,
        "distance": "0.021183850000818",
        "note": "0",
        "idnodea": 1368366566,
        "lata": "45.7682081",
        "lona": "4.8589294",
        "idnodeb": 1368366577,
        "latb": "45.7683578",
        "lonb": "4.8587605"
    },
    {
        "id": 4584,
        "distance": "0.06261665391307",
        "note": "0",
        "idnodea": 1368366577,
        "lata": "45.7683578",
        "lona": "4.8587605",
        "idnodeb": 26035011,
        "latb": "45.7685297",
        "lonb": "4.8585705"
    },
    {
        "id": 4585,
        "distance": "0.11940429735229",
        "note": "0",
        "idnodea": 26035011,
        "lata": "45.7685297",
        "lona": "4.8585705",
        "idnodeb": 26035008,
        "latb": "45.7688179",
        "lonb": "4.858252"
    },
    {
        "id": 4587,
        "distance": "0.035045772082238",
        "note": "0",
        "idnodea": 26035008,
        "lata": "45.7688179",
        "lona": "4.858252",
        "idnodeb": 26035009,
        "latb": "45.7685061",
        "lonb": "4.8581859"
    },
    {
        "id": 4602,
        "distance": "0.04355833584638",
        "note": "0",
        "idnodea": 26035063,
        "lata": "45.767952",
        "lona": "4.8591658",
        "idnodeb": 378175582,
        "latb": "45.7683425",
        "lonb": "4.8591899"
    },
    {
        "id": 4604,
        "distance": "0.060212580077342",
        "note": "0",
        "idnodea": 25468024,
        "lata": "45.7681272",
        "lona": "4.8617441",
        "idnodeb": 25468020,
        "latb": "45.7681427",
        "lonb": "4.8625201"
    },
    {
        "id": 4605,
        "distance": "0.095076147979964",
        "note": "0",
        "idnodea": 25468021,
        "lata": "45.7672903",
        "lona": "4.8626171",
        "idnodeb": 25468020,
        "latb": "45.7681427",
        "lonb": "4.8625201"
    },
    {
        "id": 4606,
        "distance": "0.063571134712438",
        "note": "0",
        "idnodea": 25468020,
        "lata": "45.7681427",
        "lona": "4.8625201",
        "idnodeb": 1678246930,
        "latb": "45.7687131",
        "lonb": "4.8624641"
    },
    {
        "id": 4607,
        "distance": "0.056753176314919",
        "note": "0",
        "idnodea": 25468020,
        "lata": "45.7681427",
        "lona": "4.8625201",
        "idnodeb": 25468019,
        "latb": "45.7681518",
        "lonb": "4.8632517"
    },
    {
        "id": 4608,
        "distance": "0.06447117669635",
        "note": "0",
        "idnodea": 26295043,
        "lata": "45.7687281",
        "lona": "4.8631601",
        "idnodeb": 25468019,
        "latb": "45.7681518",
        "lonb": "4.8632517"
    },
    {
        "id": 4609,
        "distance": "0.2031943971713",
        "note": "0",
        "idnodea": 25468019,
        "lata": "45.7681518",
        "lona": "4.8632517",
        "idnodeb": 25468003,
        "latb": "45.7663306",
        "lonb": "4.8634654"
    },
    {
        "id": 4610,
        "distance": "0.12130516019493",
        "note": "0",
        "idnodea": 25468019,
        "lata": "45.7681518",
        "lona": "4.8632517",
        "idnodeb": 25468017,
        "latb": "45.768264",
        "lonb": "4.8648074"
    },
    {
        "id": 4612,
        "distance": "0.47272671359311",
        "note": "0",
        "idnodea": 25468017,
        "lata": "45.768264",
        "lona": "4.8648074",
        "idnodeb": 25468004,
        "latb": "45.7663181",
        "lonb": "4.8648288"
    },
    {
        "id": 4613,
        "distance": "0.076919528070399",
        "note": "0",
        "idnodea": 25468017,
        "lata": "45.768264",
        "lona": "4.8648074",
        "idnodeb": 25468018,
        "latb": "45.7683314",
        "lonb": "4.8657944"
    },
    {
        "id": 4615,
        "distance": "0.028375873592858",
        "note": "0",
        "idnodea": 25468018,
        "lata": "45.7683314",
        "lona": "4.8657944",
        "idnodeb": 25468013,
        "latb": "45.7680762",
        "lonb": "4.8657959"
    },
    {
        "id": 4628,
        "distance": "0.08155624656131",
        "note": "0",
        "idnodea": 54704577,
        "lata": "45.7652296",
        "lona": "4.8699265",
        "idnodeb": 54704569,
        "latb": "45.7652108",
        "lonb": "4.8688754"
    },
    {
        "id": 6030,
        "distance": "0.2213243615133",
        "note": "0",
        "idnodea": 26291349,
        "lata": "45.7690536",
        "lona": "4.8604944",
        "idnodeb": 376377850,
        "latb": "45.7672616",
        "lonb": "4.8616329"
    },
    {
        "id": 6522,
        "distance": "0.11210394850559",
        "note": "0",
        "idnodea": 25468012,
        "lata": "45.7672997",
        "lona": "4.863354",
        "idnodeb": 25468010,
        "latb": "45.7673862",
        "lonb": "4.864794"
    },
    {
        "id": 6524,
        "distance": "0.09760771990585",
        "note": "0",
        "idnodea": 25468010,
        "lata": "45.7673862",
        "lona": "4.864794",
        "idnodeb": 25468017,
        "latb": "45.768264",
        "lonb": "4.8648074"
    },
    {
        "id": 6525,
        "distance": "0.014218709483234",
        "note": "0",
        "idnodea": 25468010,
        "lata": "45.7673862",
        "lona": "4.864794",
        "idnodeb": 2282851220,
        "latb": "45.767399",
        "lonb": "4.8649764"
    },
    {
        "id": 6526,
        "distance": "0.028177161553039",
        "note": "0",
        "idnodea": 25468011,
        "lata": "45.7671788",
        "lona": "4.8647966",
        "idnodeb": 2282851220,
        "latb": "45.767399",
        "lonb": "4.8649764"
    },
    {
        "id": 6527,
        "distance": "0.099645004419453",
        "note": "0",
        "idnodea": 2282851220,
        "lata": "45.767399",
        "lona": "4.8649764",
        "idnodeb": 25468013,
        "latb": "45.7680762",
        "lonb": "4.8657959"
    },
    {
        "id": 8902,
        "distance": "0.1622450443041",
        "note": "0",
        "idnodea": 1367957773,
        "lata": "45.7662382",
        "lona": "4.8594448",
        "idnodeb": 1367957771,
        "latb": "45.7662444",
        "lonb": "4.8596076"
    },
    {
        "id": 8938,
        "distance": "0.0014176181161577",
        "note": "0",
        "idnodea": 2195988615,
        "lata": "45.7662446",
        "lona": "4.8590812",
        "idnodeb": 1778350879,
        "latb": "45.7662444",
        "lonb": "4.8590629"
    },
    {
        "id": 8940,
        "distance": "0.2531684285396",
        "note": "0",
        "idnodea": 25310866,
        "lata": "45.7683986",
        "lona": "4.8569843",
        "idnodeb": 25310910,
        "latb": "45.7661294",
        "lonb": "4.8569474"
    },
    {
        "id": 8941,
        "distance": "0.10526595995528",
        "note": "0",
        "idnodea": 25310910,
        "lata": "45.7661294",
        "lona": "4.8569474",
        "idnodeb": 2072612784,
        "latb": "45.7651923",
        "lonb": "4.8571395"
    },
    {
        "id": 8943,
        "distance": "0.089944800735531",
        "note": "0",
        "idnodea": 1368366556,
        "lata": "45.7670326",
        "lona": "4.8580993",
        "idnodeb": 25310913,
        "latb": "45.7662241",
        "lonb": "4.8581372"
    },
    {
        "id": 8944,
        "distance": "0.071836913354739",
        "note": "0",
        "idnodea": 1778350879,
        "lata": "45.7662444",
        "lona": "4.8590629",
        "idnodeb": 25310913,
        "latb": "45.7662241",
        "lonb": "4.8581372"
    },
    {
        "id": 8945,
        "distance": "0.092885050799788",
        "note": "0",
        "idnodea": 25310913,
        "lata": "45.7662241",
        "lona": "4.8581372",
        "idnodeb": 25310910,
        "latb": "45.7661294",
        "lonb": "4.8569474"
    },
    {
        "id": 8946,
        "distance": "0.10825591840843",
        "note": "0",
        "idnodea": 25310913,
        "lata": "45.7662241",
        "lona": "4.8581372",
        "idnodeb": 26035104,
        "latb": "45.7652512",
        "lonb": "4.8581907"
    },
    {
        "id": 8947,
        "distance": "0.081799888629936",
        "note": "0",
        "idnodea": 2072612784,
        "lata": "45.7651923",
        "lona": "4.8571395",
        "idnodeb": 26035104,
        "latb": "45.7652512",
        "lonb": "4.8581907"
    },
    {
        "id": 8951,
        "distance": "0.025175321343722",
        "note": "0",
        "idnodea": 1368366540,
        "lata": "45.7658095",
        "lona": "4.8592099",
        "idnodeb": 1368366537,
        "latb": "45.7658143",
        "lonb": "4.8595344"
    },
    {
        "id": 8952,
        "distance": "0.047394313241733",
        "note": "0",
        "idnodea": 26035131,
        "lata": "45.7662401",
        "lona": "4.8595064",
        "idnodeb": 1368366537,
        "latb": "45.7658143",
        "lonb": "4.8595344"
    },
    {
        "id": 8953,
        "distance": "0.053754772404575",
        "note": "0",
        "idnodea": 1368366537,
        "lata": "45.7658143",
        "lona": "4.8595344",
        "idnodeb": 26035111,
        "latb": "45.7653311",
        "lonb": "4.8595568"
    },
    {
        "id": 9342,
        "distance": "0.061471441475862",
        "note": "0",
        "idnodea": 1384310576,
        "lata": "45.7686616",
        "lona": "4.8597934",
        "idnodeb": 2069187831,
        "latb": "45.7690066",
        "lonb": "4.8604127"
    },
    {
        "id": 9496,
        "distance": "0.070593876794851",
        "note": "0",
        "idnodea": 26035040,
        "lata": "45.7670213",
        "lona": "4.8571893",
        "idnodeb": 1368366556,
        "latb": "45.7670326",
        "lonb": "4.8580993"
    },
    {
        "id": 9996,
        "distance": "0.021088301450678",
        "note": "0",
        "idnodea": 378212455,
        "lata": "45.7687038",
        "lona": "4.8619835",
        "idnodeb": 1423304208,
        "latb": "45.7686989",
        "lonb": "4.8617117"
    },
    {
        "id": 9998,
        "distance": "0.012793478944392",
        "note": "0",
        "idnodea": 25468023,
        "lata": "45.7672665",
        "lona": "4.8617977",
        "idnodeb": 376377850,
        "latb": "45.7672616",
        "lonb": "4.8616329"
    },
    {
        "id": 10252,
        "distance": "0.069351040795387",
        "note": "0",
        "idnodea": 2195988615,
        "lata": "45.7662446",
        "lona": "4.8590812",
        "idnodeb": 2195988614,
        "latb": "45.766868",
        "lonb": "4.8590526"
    },
    {
        "id": 6523,
        "distance": "0.023061720708125",
        "note": "0",
        "idnodea": 25468011,
        "lata": "45.7671788",
        "lona": "4.8647966",
        "idnodeb": 25468010,
        "latb": "45.7673862",
        "lonb": "4.864794"
    },
    {
        "id": 8942,
        "distance": "0.078461220220028",
        "note": "0",
        "idnodea": 25310910,
        "lata": "45.7661294",
        "lona": "4.8569474",
        "idnodeb": 1954994821,
        "latb": "45.7660182",
        "lonb": "4.855949"
    },
    {
        "id": 8948,
        "distance": "0.10634565593974",
        "note": "0",
        "idnodea": 26035104,
        "lata": "45.7652512",
        "lona": "4.8581907",
        "idnodeb": 26035111,
        "latb": "45.7653311",
        "lonb": "4.8595568"
    }
]